Workbook
Name データ計算式: データ!$S$1
Name データ計算式数式: データ!$T$1
Name データ計算数量: データ!$R$1
Name データ建設資機材コード: データ!$L$1
Name データ建設資機材コード: データ!$L$1
Name データ見積単価: データ!$H$1
Name データ見積単価: データ!$H$1
Name データ子: データ!$B$1
Name データ子: データ!$B$1
Name データ自動数量: データ!$R$1
Name データ親: データ!$A$1
Name データ親: データ!$A$1
Name データ数量: データ!$F$1
Name データ数量: データ!$F$1
Name データ単位: データ!$G$1
Name データ単位: データ!$G$1
Name データ通: データ!$C$1
Name データ通: データ!$C$1
Name データ定価: データ!$J$1
Name データ定価: データ!$J$1
Name データ摘要: データ!$E$1
Name データ摘要: データ!$E$1
Name データ発注コード: データ!$N$1
Name データ発注コード: データ!$N$1
Name データ発注単価: データ!$I$1
Name データ発注単価: データ!$I$1
Name データ備考: データ!$O$1
Name データ備考: データ!$O$1
Name データ部位: データ!$P$1
Name データ部材コード: データ!$K$1
Name データ部材コード: データ!$K$1
Name データ補給率: データ!$Q$1
Name データ名称: データ!$D$1
Name データ名称: データ!$D$1
Name データ要素コード: データ!$M$1
Name データ要素コード: データ!$M$1
Name ワークファイルパス: 条件!$C$3
Name 見積金額: #REF!
Name 見積金額: 明細書!$G$1
Name 見積金額: #REF!
Name 見積数量: #REF!
Name 見積数量: 明細書!$D$1
Name 見積数量: #REF!
Name 見積単価: #REF!
Name 見積単価: 明細書!$F$1
Name 見積単価: #REF!
Name 条件延床面積: 条件!$E$14
Name 条件延床面積坪: 条件!$E$15
Name 条件会社FAX: 条件!$H$16
Name 条件会社MAIL: 条件!$H$18
Name 条件会社TEL: 条件!$H$15
Name 条件会社URL: 条件!$H$17
Name 条件会社事業所名: 条件!$H$11
Name 条件会社住所１: 条件!$H$13
Name 条件会社住所２: 条件!$H$14
Name 条件会社名: 条件!$H$10
Name 条件会社郵便番号: 条件!$H$12
Name 条件金額まるめ: 条件!$E$16
Name 条件経費行書式: 条件!$E$27
Name 条件見積金額合計: 条件!$E$17

Sheet 表紙
E3: =条件!H28 -> 契約後変更 | P3: 御見積書
AC5: 見積番号： | AF5: =条件!H26 -> 25-2507(13)-H230堀-NO-FT⑦04B
AC6: 提 出 日 ： | AF6: =条件!H27 -> 45955
B7: =条件!$E$13 -> 古居 徹朗 様・古居 百恵
R8: 様 | AB8: =IF(条件!$H$10="","日本住建株式会社",条件!$H$10) -> 日本住建株式会社
AG10: 代表取締役 兵藤大祐
C11: 下記の通り、お見積り申し上げます。 | AC11: 〒 | AD11: 446-0043
AC12: =IF(条件!$H$13="","愛知県安城市城南町1-1-1",条件!$H$13) -> 愛知県安城市城南町1-1-1
AC13: TEL： | AE13: =IF(条件!$H$15="","0566-74-1011（代）",条件!$H$15) -> 0566-74-1011（代）
B14: 御見積金額（税込） | M14: =条件!$E$17 -> 35971100 | V14: - | AC14: FAX： | AE14: =IF(条件!$H$16="","0566-74-3888",条件!$H$16) -> 0566-74-3888
AC15: URL： | AE15: https://www.nipponjuken.co.jp/
K16: ( | L16: 税別金額 | P16: =条件!$E$17-条件!$E$18 -> 32701000 | W16: ―）
K17: ( | L17: 消費税 | P17: =条件!$E$18 -> 3270100 | W17: ―）
B19: 工事名 | G19: =条件!$E$10 -> 古居 徹朗 様・古居 百恵 様邸新築工事⑦
B20: 工事場所 | G20: =条件!$E$11 -> 西尾市戸ケ崎
B21: 工期 | G21: お打ち合わせによる | AB21: =IF(AE21=0,"","プラン名：") -> プラン名： | AE21: =条件!H21 -> ⑦ 自由設計プラン
B22: 見積有効期限 | G22: 提出日より1か月間 | AB22: 図面日付： | AE22: =条件!H20 -> 45942
B23: 工事概要 | G23: 工法： | I23: =条件!H19 -> 木造軸組ALL金物構造 | R23: 種別： | T23: =条件!$E$12 -> 新築 | AB23: 設計 | AE23: 工事 | AH23: 営業 | AK23: 最終承認
G24: 延床面積： | J24: =条件!E14 -> 115.3 | M24: ㎡ | O24: （ | P24: =条件!$E$15 -> 34.87 | S24: 坪）
B25: お支払い条件 | G25: 契約時10％ 着工時30％ 上棟時40％ 完成時20％+追加変更金100％ 解体工事・造成工事・地盤補強工事等の先行工事分は当該工事後100％
B26: 備考 | G26: 木材の価格及び調達情勢が不安定な為、上記有効期限経過後は再見積となります 住宅設備等が価格改定の場合、有効期限に係わらず経過期間終了後の見積金額は変更となります
G27: 【保証・保険】瑕疵担保責任保険（2000万円ｺｰｽ） ・地盤20年・躯体30年・防水20年・設備10年・その他保証書に準ずる

Sheet 明細書
A1: 項目№ | B1: 名称 | C1: 摘要 | D1: 見積数量 | E1: 単位 | F1: 見積単価 | G1: 見積金額
A2: 1 | B2: 仮設工事 | D2: 1 | E2: 式 | F2: =G61 -> 914151 | G2: =ROUNDDOWN(D2*F2,0) -> 914151
A3: 2 | B3: 基礎工事 | D3: 1 | E3: 式 | F3: =G101 -> 2275605 | G3: =ROUNDDOWN(D3*F3,0) -> 2275605
A4: 3 | B4: 木工事 | D4: 1 | E4: 式 | F4: =G121 -> 12317611 | G4: =ROUNDDOWN(D4*F4,0) -> 12317611
A5: 4 | B5: 断熱工事 | D5: 1 | E5: 式 | F5: =G261 -> 1256721 | G5: =ROUNDDOWN(D5*F5,0) -> 1256721
A6: 5 | B6: 屋根工事 | D6: 1 | E6: 式 | F6: =G321 -> 739277 | G6: =ROUNDDOWN(D6*F6,0) -> 739277
A7: 6 | B7: 板金・樋工事 | D7: 1 | E7: 式 | F7: =G341 -> 202780 | G7: =ROUNDDOWN(D7*F7,0) -> 202780
A8: 7 | B8: 外部建具工事 | D8: 1 | E8: 式 | F8: =G361 -> 981800 | G8: =ROUNDDOWN(D8*F8,0) -> 981800
A9: 8 | B9: 内部建具工事 | D9: 1 | E9: 式 | F9: =G381 -> 1133700 | G9: =ROUNDDOWN(D9*F9,0) -> 1133700
A10: 9 | B10: 外装工事 | D10: 1 | E10: 式 | F10: =G401 -> 2087931 | G10: =ROUNDDOWN(D10*F10,0) -> 2087931
A11: 10 | B11: 左官工事 | D11: 1 | E11: 式 | F11: =G421 -> 254156 | G11: =ROUNDDOWN(D11*F11,0) -> 254156
A12: 11 | B12: タイル工事 | D12: 1 | E12: 式 | F12: =G461 -> 254760 | G12: =ROUNDDOWN(D12*F12,0) -> 254760
A13: 12 | B13: 塗装工事 | D13: 1 | E13: 式 | F13: =G481 -> 42900 | G13: =ROUNDDOWN(D13*F13,0) -> 42900
A14: 13 | B14: 内装工事 | D14: 1 | E14: 式 | F14: =G501 -> 896446 | G14: =ROUNDDOWN(D14*F14,0) -> 896446
A15: 14 | B15: 住宅設備機器工事 | D15: 1 | E15: 式 | F15: =G521 -> 2340500 | G15: =ROUNDDOWN(D15*F15,0) -> 2340500
A16: 15 | B16: 給排水設備工事 | D16: 1 | E16: 式 | F16: =G541 -> 242900 | G16: =ROUNDDOWN(D16*F16,0) -> 242900
A17: 16 | B17: 電気設備工事 | D17: 1 | E17: 式 | F17: =G581 -> 1243650 | G17: =ROUNDDOWN(D17*F17,0) -> 1243650
A18: 17 | B18: 換気システム工事 | D18: 1 | E18: 式 | F18: =G601 -> 472052 | G18: =ROUNDDOWN(D18*F18,0) -> 472052
A19: 18 | B19: エアコン工事 | D19: 1 | E19: 式 | F19: =G621 -> 351500 | G19: =ROUNDDOWN(D19*F19,0) -> 351500
A20: 19 | B20: 太陽光発電システム工事 | D20: 1 | E20: 式 | F20: =G641 -> 981700 | G20: =ROUNDDOWN(D20*F20,0) -> 981700
A21: 20 | B21: 造作家具工事 | D21: 1 | E21: 式 | F21: =G661 -> 57200 | G21: =ROUNDDOWN(D21*F21,0) -> 57200
A22: 21 | B22: 雑工事 | D22: 1 | E22: 式 | F22: =G681 -> 160385 | G22: =ROUNDDOWN(D22*F22,0) -> 160385
A23: 22 | B23: 管理費 | D23: 1 | F23: 0 | G23: =ROUNDDOWN(SUM(G1:G22)*0.03,0) -> 876231
A24: 23 | B24: 屋外付帯工事 | D24: 1 | E24: 式 | F24: =G701 -> 1347250 | G24: =ROUNDDOWN(D24*F24,0) -> 1347250
A25: 24 | B25: 諸費用 | D25: 1 | E25: 式 | F25: =G721 -> 1270000 | G25: =ROUNDDOWN(D25*F25,0) -> 1270000
A26: 25 | B26: 端数値引き | G26: -206
B27: 消費税等 | G27: =ROUNDDOWN(SUM(G2:G26)*10/100,0) -> 3270100
B41: 総合計 | G41: =SUM(G2:G40) -> 35971100
A42: 1 | B42: 仮設工事
A44: 1-1 | B44: 安全対策費 | D44: 1 | E44: 式 | F44: =G81 -> 387300 | G44: =ROUNDDOWN(D44*F44,0) -> 387300
A45: 1-2 | B45: 外部足場組 | C45: 養生ﾈｯﾄ等含む | D45: 256.1 | E45: ㎡ | F45: 900 | G45: =ROUNDDOWN(D45*F45,0) -> 230490
A46: 1-3 | B46: 仮設ﾄｲﾚ | D46: 1 | E46: 式 | F46: 35800 | G46: =ROUNDDOWN(D46*F46,0) -> 35800
A47: 1-4 | B47: 廃材処分費 | D47: 117.37 | E47: ㎡ | F47: 1500 | G47: =ROUNDDOWN(D47*F47,0) -> 176055
A48: 1-5 | B48: 運搬費 | D48: 117.37 | E48: ㎡ | F48: 720 | G48: =ROUNDDOWN(D48*F48,0) -> 84506
B61: 合計 | G61: =SUM(G43:G60) -> 914151
A62: 1-1 | B62: 安全対策費
A64: 1-1-1 | B64: 駐車場代 | C64: ※駐車スペースある場合もマイナスしない | D64: 1 | E64: 式 | F64: 171500 | G64: =ROUNDDOWN(D64*F64,0) -> 171500
A65: 1-1-2 | B65: 基礎廻り養生ｼｰﾄ | D65: 1 | E65: 式 | F65: 22900 | G65: =ROUNDDOWN(D65*F65,0) -> 22900
A66: 1-1-3 | B66: 安全対策費 | C66: 120㎡以下 | D66: 1 | E66: 式 | F66: 142900 | G66: =ROUNDDOWN(D66*F66,0) -> 142900
A67: 1-1-4 | B67: 整地費用 | C67: ※整地不要の場合もマイナスしない | D67: 1 | E67: 式 | F67: 50000 | G67: =ROUNDDOWN(D67*F67,0) -> 50000
B81: 合計 | G81: =SUM(G63:G80) -> 387300
A82: 2 | B82: 基礎工事
A84: 2-1 | B84: 水盛り･遣方 | D84: 1 | E84: 式 | F84: 28600 | G84: =ROUNDDOWN(D84*F84,0) -> 28600
A85: 2-2 | B85: ﾍﾞﾀ基礎 | D85: 62.02 | E85: ㎡ | F85: 28200 | G85: =ROUNDDOWN(D85*F85,0) -> 1748964
A86: 2-3 | B86: 人通口補強 | C86: 60㎡以下 | D86: 1 | E86: 式 | F86: 137200 | G86: =ROUNDDOWN(D86*F86,0) -> 137200
A87: 2-4 | B87: 下地土間ｺﾝｸﾘｰﾄ | C87: 玄関･ﾎﾟｰﾁ | D87: 8.2 | E87: ㎡ | F87: 5800 | G87: =ROUNDDOWN(D87*F87,0) -> 47560
A88: 2-5 | B88: ﾎﾟﾝﾌﾟ車 | D88: 2 | E88: 台 | F88: 57200 | G88: =ROUNDDOWN(D88*F88,0) -> 114400
A89: 2-6 | B89: 深基礎 | C89: 高低差450㎜以下 | D89: 16.39 | E89: ｍ | F89: 11500 | G89: =ROUNDDOWN(D89*F89,0) -> 188485
A90: 2-7 | B90: 布基礎 | D90: 0.46 | E90: ｍ | F90: 22600 | G90: =ROUNDDOWN(D90*F90,0) -> 10396
B91: ※地盤調査結果や、既設CB積の底盤位置により、
B92: 持出し基礎等の特殊工事が必要となった場合は別見積となります。
B101: 合計 | G101: =SUM(G83:G100) -> 2275605
A102: 3 | B102: 木工事
A104: 3-1 | B104: 軸組・羽柄材・PC | D104: 1 | E104: 式 | F104: =G141 -> 3943795 | G104: =ROUNDDOWN(D104*F104,0) -> 3943795
A105: 3-2 | B105: 建材・下地材 | D105: 1 | E105: 式 | F105: =G201 -> 4333718 | G105: =ROUNDDOWN(D105*F105,0) -> 4333718
A106: 3-3 | B106: 大工手間 | D106: 1 | E106: 式 | F106: =G241 -> 3484098 | G106: =ROUNDDOWN(D106*F106,0) -> 3484098
A107: 3-4 | B107: 1階床 無垢ﾌﾛｰﾘﾝｸﾞ（標準） | C107: 北恵 ※施工費込 | D107: 10 | E107: 坪 | F107: 31200 | G107: =ROUNDDOWN(D107*F107,0) -> 312000
A108: 3-5 | B108: 2階床 ﾌﾛｰﾘﾝｸﾞ貼 | C108: 朝日ｳｯﾄﾞﾃｯｸ MRX3P | D108: 16 | E108: 坪 | F108: 11500 | G108: =ROUNDDOWN(D108*F108,0) -> 184000
A109: 3-6 | B109: 水廻り床 | C109: ｲｸﾀ ｸﾙｰﾄﾞﾌﾛｰﾘﾝｸﾞ ※ｼﾞｮｲﾝﾄｼｰﾙ施工 | D109: 3 | E109: 坪 | F109: 20000 | G109: =ROUNDDOWN(D109*F109,0) -> 60000
B121: 合計 | G121: =SUM(G103:G120) -> 12317611
A122: 3-1 | B122: 軸組・羽柄材・PC
A124: 3-1-1 | B124: 【ALL金物工法】木造構造材･羽柄材･ﾌﾟﾚｶｯﾄ | C124: 基本 本体+付帯 | D124: 35.51 | E124: 坪 | F124: 102900 | G124: =ROUNDDOWN(D124*F124,0) -> 3653979
A125: 3-1-2 | B125: 金物費捻出 | D125: -1 | E125: 式 | F125: 85800 | G125: =ROUNDDOWN(D125*F125,0) -> -85800
A126: 3-1-3 | B126: 割増A：建物難易度 | C126: 外部入隅の数 | D126: 4 | E126: ヶ所 | F126: 21500 | G126: =ROUNDDOWN(D126*F126,0) -> 86000
A127: 3-1-4 | B127: 割増B：2階比 | C127: 1階-2階 | D127: 1.06 | E127: 坪 | F127: 3600 | G127: =ROUNDDOWN(D127*F127,0) -> 3816
A128: 3-1-5 | B128: 化粧柱 | C128: 化粧柱[個数] | D128: 1 | E128: 本 | F128: 17200 | G128: =ROUNDDOWN(D128*F128,0) -> 17200
A129: 3-1-6 | B129: 金物費 | D129: 1 | E129: 式 | F129: 85800 | G129: =ROUNDDOWN(D129*F129,0) -> 85800
A130: 3-1-7 | B130: 遠方割増 | C130: 都度計算 ※西尾市、該当なし | D130: 1 | E130: 式 | F130: 0 | G130: =ROUNDDOWN(D130*F130,0) -> 0
A131: 3-1-8 | B131: 構造追加費 | C131: 基本の5％ﾍﾞｰｽ | D131: 1 | E131: 式 | F131: 182800 | G131: =ROUNDDOWN(D131*F131,0) -> 182800
B141: 合計 | G141: =SUM(G123:G140) -> 3943795
A142: 3-2 | B142: 建材・下地材
A144: 3-2-1 | B144: 下地材 | C144: 基本 | D144: 35.51 | E144: 坪 | F144: 37200 | G144: =ROUNDDOWN(D144*F144,0) -> 1320972
A145: 3-2-2 | B145: 下地材(割増) | C145: 入隅ヶ所数 | D145: 4 | E145: ヶ所 | F145: 14300 | G145: =ROUNDDOWN(D145*F145,0) -> 57200
A146: 3-2-3 | B146: 軒天無し | C146: ｱｽﾉﾝ8㎜ 無塗装板 | D146: 1 | E146: 式 | F146: -14300 | G146: =ROUNDDOWN(D146*F146,0) -> -14300
A147: 3-2-4 | B147: 養生費・補修費捻出 | D147: 1 | E147: 式 | F147: -142900 | G147: =ROUNDDOWN(D147*F147,0) -> -142900
A148: 3-2-5 | B148: 玄関框 | C148: ﾌﾟﾚｲﾘｰﾎｰﾑｽﾞｽﾏｰﾄ框 | D148: 1 | E148: 本 | F148: 14300 | G148: =ROUNDDOWN(D148*F148,0) -> 14300
A149: 3-2-6 | B149: 上框(挽板･無垢床用) | C149: W6尺 床合わせ面材貼り | D149: 2 | E149: 本 | F149: 18600 | G149: =ROUNDDOWN(D149*F149,0) -> 37200
A150: 3-2-7 | B150: 床組無し(内部土間床) | C150: 内部土間床･ｲﾝﾅｰｶﾞﾚｰｼﾞ･外部収納等 | D150: 5.59 | E150: ㎡ | F150: -2900 | G150: =ROUNDDOWN(D150*F150,0) -> -16211
A151: 3-2-8 | B151: 階段(1～2階) | C151: 標準箱型6段回り以下 | D151: 1 | E151: ｾｯﾄ | F151: 151500 | G151: =ROUNDDOWN(D151*F151,0) -> 151500
A152: 3-2-9 | B152: 階段手摺 | C152: 丸棒手摺（金具ｶﾜｼﾞｭﾝ） | D152: 1 | E152: ｾｯﾄ | F152: 43500 | G152: =ROUNDDOWN(D152*F152,0) -> 43500
A153: 3-2-10 | B153: 枕棚+ﾊﾟｲﾌﾟ | C153: W6尺以下 | D153: 6 | E153: ヶ所 | F153: 17200 | G153: =ROUNDDOWN(D153*F153,0) -> 103200
A154: 3-2-11 | B154: 下地補強 | D154: 3 | E154: ヶ所 | F154: 28600 | G154: =ROUNDDOWN(D154*F154,0) -> 85800
A155: 3-2-12 | B155: 笠木 | C155: ｺﾞﾑ集成材 ｳﾚﾀﾝ塗装 | D155: 2 | E155: 本 | F155: 20000 | G155: =ROUNDDOWN(D155*F155,0) -> 40000
A156: 3-2-13 | B156: 大壁和室造作材 | C156: 付鴨居無し | D156: 2.69 | E156: ㎡ | F156: 8600 | G156: =ROUNDDOWN(D156*F156,0) -> 23134
A157: 3-2-14 | B157: 床上げ用材料（框別） | D157: 2.69 | E157: ㎡ | F157: 8600 | G157: =ROUNDDOWN(D157*F157,0) -> 23134
A158: 3-2-15 | B158: 中段・枕棚ｾｯﾄ | C158: W6尺以下 | D158: 1 | E158: ヶ所 | F158: 22900 | G158: =ROUNDDOWN(D158*F158,0) -> 22900
A159: 3-2-16 | B159: 鋼板屋根遮音下地 | C159: ﾋﾞﾙﾎﾞｰﾄﾞ9㎜ | D159: 96.01 | E159: ㎡ | F159: 1100 | G159: =ROUNDDOWN(D159*F159,0) -> 105611
A160: 3-2-17 | B160: 外壁透湿防水シート | C160: ﾀｲﾍﾞｯｸ（ﾄﾞﾚｲﾝﾗｯﾌﾟ又はﾊｳｽﾗｯﾌﾟ） | D160: 193.53 | E160: ㎡ | F160: 800 | G160: =ROUNDDOWN(D160*F160,0) -> 154824
A161: 3-2-18 | B161: 耐力面材 | C161: ﾀﾞｲﾗｲﾄ MS9 | D161: 87 | E161: 枚 | F161: 4300 | G161: =ROUNDDOWN(D161*F161,0) -> 374100
A162: 3-2-19 | B162: 制震ﾀﾞﾝﾊﾟｰ | C162: MIRAIE | D162: 4 | E162: 本 | F162: 86500 | G162: =ROUNDDOWN(D162*F162,0) -> 346000
A163: 3-2-20 | B163: 窓枠(掃出し3方､中連4方) | C163: LIXIL ﾗｼｯｻS ｽﾏｰﾄ10 | D163: 12 | E163: 本 | F163: 4200 | G163: =ROUNDDOWN(D163*F163,0) -> 50400
A164: 3-2-21 | B164: 化粧巾木 | C164: LIXIL ﾗｲﾝ巾木 | D164: 37 | E164: 本 | F164: 2100 | G164: =ROUNDDOWN(D164*F164,0) -> 77700
A165: 3-2-22 | B165: ﾆｯﾁ | C165: 材工+ｸﾛｽ | D165: 1 | E165: ヶ所 | F165: 25800 | G165: =ROUNDDOWN(D165*F165,0) -> 25800
A166: 3-2-23 | B166: FB手摺りﾊｰﾌ×0.5 | C166: FB手すりﾊｰﾌ[個数] | D166: 1 | E166: ｾｯﾄ | F166: 176000 | G166: =ROUNDDOWN(D166*F166,0) -> 176000
A167: 3-2-24 | B167: 換気部材（一般用・破風レス対応） | C167: 軒+ケラバ長さ換算追加 | D167: 55.61 | E167: ｍ | F167: 2200 | G167: =ROUNDDOWN(D167*F167,0) -> 122342
A168: 3-2-25 | B168: 床ｶﾞﾗﾘ変更 | C168: 樹脂→オーク無垢（無塗装） | D168: 6 | E168: ヶ所 | F168: 0 | G168: =ROUNDDOWN(D168*F168,0) -> 0
A169: 3-2-26 | B169: 床ｶﾞﾗﾘ変更 | C169: 塗装費のみ | D169: 1 | E169: 式 | F169: 29000 | G169: =ROUNDDOWN(D169*F169,0) -> 29000
... A171: 3-2-28 | B171: 小屋裏耐力面材：屋根勾配3寸超6寸未満 | C171: ダイライトMS9片面張 | D171: 1 | E171: 式 | F171: 57200 | G171: =ROUNDDOWN(D171*F171,0) -> 57200
A172: 3-2-29 | B172: 床養生費 | D172: 1 | E172: 式 | F172: 71500 | G172: =ROUNDDOWN(D172*F172,0) -> 71500
A173: 3-2-30 | B173: 補修費 | D173: 1 | E173: 式 | F173: 71500 | G173: =ROUNDDOWN(D173*F173,0) -> 71500
...

Sheet データ
A1: 親 | B1: 子 | C1: 通 | D1: 名称 | E1: 摘要 | F1: 数量 | G1: 単位 | H1: 見積単価 | I1: 発注単価 | J1: 定価 | K1: 部材コード | L1: 建設資機材コード | M1: 要素コード | N1: 発注lコード | O1: 備考 | P1: 部位 | Q1: 補給率 | R1: 計算数量 | S1: 計算式 | T1: 計算式数式
A2: 0 | B2: 1 | C2: 0 | D2: 仮設工事 | F2: 1 | G2: 式 | H2: 914151 | I2: 625715 | J2: 0
A3: 0 | B3: 11 | C3: 0 | D3: 基礎工事 | F3: 1 | G3: 式 | H3: 2275605 | I3: 1588963 | J3: 0
A4: 0 | B4: 21 | C4: 0 | D4: 木工事 | F4: 1 | G4: 式 | H4: 12317611 | I4: 7910157 | J4: 0
A5: 0 | B5: 108 | C5: 0 | D5: 断熱工事 | F5: 1 | G5: 式 | H5: 1256721 | I5: 871719 | J5: 0
A6: 0 | B6: 123 | C6: 0 | D6: 屋根工事 | F6: 1 | G6: 式 | H6: 739277 | I6: 513653 | J6: 0
A7: 0 | B7: 126 | C7: 0 | D7: 板金・樋工事 | F7: 1 | G7: 式 | H7: 202780 | I7: 141496 | J7: 0
A8: 0 | B8: 130 | C8: 0 | D8: 外部建具工事 | F8: 1 | G8: 式 | H8: 981800 | I8: 687000 | J8: 0
A9: 0 | B9: 141 | C9: 0 | D9: 内部建具工事 | F9: 1 | G9: 式 | H9: 1133700 | I9: 792920 | J9: 0
A10: 0 | B10: 158 | C10: 0 | D10: 外装工事 | F10: 1 | G10: 式 | H10: 2087931 | I10: 1449077 | J10: 0
A11: 0 | B11: 165 | C11: 0 | D11: 左官工事 | F11: 1 | G11: 式 | H11: 254156 | I11: 176780 | J11: 0
A12: 0 | B12: 172 | C12: 0 | D12: タイル工事 | F12: 1 | G12: 式 | H12: 254760 | I12: 177868 | J12: 0
A13: 0 | B13: 174 | C13: 0 | D13: 塗装工事 | F13: 1 | G13: 式 | H13: 42900 | I13: 30000 | J13: 0
... A22: 0 | B22: 247 | C22: 0 | D22: 雑工事 | F22: 1 | G22: 式 | H22: 160385 | I22: 111543 | J22: 0
A23: 0 | B23: 0 | C23: 0 | D23: 諸経費 | F23: 1 | H23: 0.03 | I23: 0.02
A24: 0 | B24: 252 | C24: 0 | D24: 屋外付帯工事 | F24: 1 | G24: 式 | H24: 1347250 | I24: 927282 | J24: 0
A25: 0 | B25: 256 | C25: 0 | D25: 諸費用 | F25: 1 | G25: 式 | H25: 1270000 | I25: 889000 | J25: 0
A26: 1 | B26: 2 | C26: 0 | D26: 安全対策費 | F26: 1 | G26: 式 | H26: 387300 | I26: 271000 | J26: 0
A27: 1 | B27: 7 | C27: 1 | D27: 外部足場組 | E27: 養生ﾈｯﾄ等含む | F27: 256.1 | G27: ㎡ | H27: 900 | I27: 600 | J27: 0 | O27: 見付面積 | P27: 基本 | Q27: 1 | R27: 256.1035 | S27: (【外壁[建具開口無し](全階) 面積】+【外壁巾木[建具開口無し](全階) 面積】+【妻壁 面積】+【外壁腰壁[建具開口無し](全階) 面積】+【手摺(外部) 面積】*0.8)*1.15 | T27: (206.6628000+14.8240000+1.2119000+0.0000000+0.0000000*0.8)*1.15
A28: 1 | B28: 8 | C28: 1 | D28: 仮設ﾄｲﾚ | F28: 1 | G28: 式 | H28: 35800 | I28: 25000 | J28: 0 | P28: 基本 | Q28: 1 | R28: 1
A29: 1 | B29: 9 | C29: 1 | D29: 廃材処分費 | F29: 117.37 | G29: ㎡ | H29: 1500 | I29: 1000 | J29: 0 | O29: 施工床面積 | P29: 基本 | Q29: 1 | R29: 117.37 | S29: IF(【施工床面積[ﾄｰﾀﾙ面積表]】,【施工床面積[ﾄｰﾀﾙ面積表]】,(【部屋(全階) 面積】+【バルコニー 面積(壁芯)】)) | T29: IF(117.3700000,117.3700000,(115.3130000+0.0000000))
A30: 1 | B30: 10 | C30: 1 | D30: 運搬費 | F30: 117.37 | G30: ㎡ | H30: 720 | I30: 500 | J30: 0 | O30: 施工床面積 | P30: 基本 | Q30: 1 | R30: 117.37 | S30: IF(【施工床面積[ﾄｰﾀﾙ面積表]】,【施工床面積[ﾄｰﾀﾙ面積表]】,(【部屋(全階) 面積】+【バルコニー 面積(壁芯)】)) | T30: IF(117.3700000,117.3700000,(115.3130000+0.0000000))
A31: 2 | B31: 3 | C31: 1 | D31: 駐車場代 | E31: ※駐車スペースある場合もマイナスしない | F31: 1 | G31: 式 | H31: 171500 | I31: 120000 | J31: 0 | P31: 基本 | Q31: 1 | R31: 1
A32: 2 | B32: 4 | C32: 1 | D32: 基礎廻り養生ｼｰﾄ | F32: 1 | G32: 式 | H32: 22900 | I32: 16000 | J32: 0 | P32: 基本 | Q32: 1 | R32: 1
A33: 2 | B33: 5 | C33: 1 | D33: 安全対策費 | E33: 120㎡以下 | F33: 1 | G33: 式 | H33: 142900 | I33: 100000 | J33: 0 | P33: 基本 | Q33: 1 | R33: 1 | S33: 評価式1 ≦ 評価式2 | T33: 1
A34: 2 | B34: 6 | C34: 1 | D34: 整地費用 | E34: ※整地不要の場合もマイナスしない | F34: 1 | G34: 式 | H34: 50000 | I34: 35000 | J34: 0 | P34: 基本 | Q34: 1 | R34: 1
A35: 11 | B35: 12 | C35: 1 | D35: 水盛り･遣方 | F35: 1 | G35: 式 | H35: 28600 | I35: 20000 | J35: 0 | P35: 基本 | Q35: 1 | R35: 1
A36: 11 | B36: 13 | C36: 1 | D36: ﾍﾞﾀ基礎 | F36: 62.02 | G36: ㎡ | H36: 28200 | I36: 19700 | J36: 0 | O36: 基礎伏図ﾍﾞﾀ基礎面積※ない場合は1F部屋面積から集 | P36: 基本 | Q36: 1 | R36: 62.0209 | S36: 【床(1階) 面積[配置図ﾄｰﾀﾙ面積表]】+【ポーチ 面積】 | T36: 59.4100000+2.6109000
A37: 11 | B37: 14 | C37: 1 | D37: 人通口補強 | E37: 60㎡以下 | F37: 1 | G37: 式 | H37: 137200 | I37: 96000 | J37: 0 | P37: 基本 | Q37: 1 | R37: 1 | S37: 評価式1 ≦ 評価式2 | T37: 1
A38: 11 | B38: 15 | C38: 1 | D38: 下地土間ｺﾝｸﾘｰﾄ | E38: 玄関･ﾎﾟｰﾁ | F38: 8.2 | G38: ㎡ | H38: 5800 | I38: 4000 | J38: 0 | O38: 土間ﾀｲﾌﾟの部屋･ﾎﾟｰﾁ･犬走面積から集計 | P38: 基本 | Q38: 1 | R38: 8.2006 | S38: 【部屋面積 (1階 玄関)】+【ポーチ 面積】 | T38: 5.5897000+2.6109000
A39: 11 | B39: 16 | C39: 1 | D39: ﾎﾟﾝﾌﾟ車 | F39: 2 | G39: 台 | H39: 57200 | I39: 40000 | J39: 0 | P39: 基本 | Q39: 1 | R39: 2
A40: 11 | B40: 17 | C40: 1 | D40: 深基礎 | E40: 高低差450㎜以下 | F40: 16.39 | G40: ｍ | H40: 11500 | I40: 8000 | J40: 0 | P40: 積算ｼﾝﾎﾞﾙ | Q40: 1 | R40: 16.38
A41: 11 | B41: 18 | C41: 1 | D41: 布基礎 | F41: 0.46 | G41: ｍ | H41: 22600 | I41: 15760 | J41: 0 | P41: 積算ｼﾝﾎﾞﾙ | Q41: 1 | R41: 0.455
A42: 11 | B42: 19 | C42: 1 | D42: ※地盤調査結果や、既設CB積の底盤位置により、 | E42: 持出し基礎等の特殊工事が必要となった場合は | F42: 1 | H42: 0 | I42: 0 | J42: 0 | P42: 基本 | Q42: 1 | R42: 1
A43: 11 | B43: 20 | C43: 1 | E43: 別見積となります。 | F43: 1 | H43: 0 | I43: 0 | J43: 0 | P43: 基本 | Q43: 1 | R43: 1
A44: 21 | B44: 22 | C44: 0 | D44: 軸組・羽柄材・PC | F44: 1 | G44: 式 | H44: 3943795 | I44: 2759270 | J44: 0
A45: 21 | B45: 31 | C45: 0 | D45: 建材・下地材 | F45: 1 | G45: 式 | H45: 4333718 | I45: 2680197 | J45: 0
A46: 21 | B46: 77 | C46: 0 | D46: 大工手間 | F46: 1 | G46: 式 | H46: 3484098 | I46: 2082690 | J46: 0
A47: 21 | B47: 105 | C47: 1 | D47: 1階床 無垢ﾌﾛｰﾘﾝｸﾞ（標準） | E47: 北恵 ※施工費込 | F47: 10 | G47: 坪 | H47: 31200 | I47: 21800 | J47: 0 | P47: 基本 | Q47: 1 | R47: 38.7137 | S47: 【床 面積 (1階 ホール・廊下)】+【床 面積 (1階 食事室)】+【床 面積 (1階 居間)】+【床 面積 (1階 台所)】+【床 面積 (1階 洋室)】+【床 面積 (1階 寝室)】+【床 面積 (1階 子供室)】+【床 面積 (1階 書斎)】+【床 面積 (1階 収納)】+【床 面積 (1階 ｳｫｰｸｲﾝｸﾛｰｾﾞｯﾄ)】+【床 面積 (1階 その他)】+【床 面積 (1階 小屋裏収納)】+【床 面積 (1階 階段室)】 | T47: 4.9686000+0.0000000+0.0000000+31.2608000+0.0000000+0.0000000+0.0000000+0.0000000+1.6562000+0.0000000+0.0000000+0.0000000+0.8281000
A48: 21 | B48: 106 | C48: 1 | D48: 2階床 ﾌﾛｰﾘﾝｸﾞ貼 | E48: 朝日ｳｯﾄﾞﾃｯｸ MRX3P | F48: 16 | G48: 坪 | H48: 11500 | I48: 8000 | J48: 0 | P48: 基本 | Q48: 1 | R48: 50.9282 | S48: 【床 面積 (2階 ホール・廊下)】+【床 面積 (2階 食事室)】+【床 面積 (2階 居間)】+【床 面積 (2階 台所)】+【床 面積 (2階 洋室)】+【床 面積 (2階 寝室)】+【床 面積 (2階 子供室)】+【床 面積 (2階 書斎)】+【床 面積 (2階 収納)】+【床 面積 (2階 ｳｫｰｸｲﾝｸﾛｰｾﾞｯﾄ)】+【床 面積 (2階 小屋裏収納)】+【床 面積 (2階 その他)】+【床 面積 (2階 小屋裏収納)】 | T48: 6.2108000+0.0000000+0.0000000+0.0000000+37.2645000+0.0000000+0.0000000+0.0000000+7.4529000+0.0000000+0.0000000+0.0000000+0.0000000
A49: 21 | B49: 107 | C49: 1 | D49: 水廻り床 | E49: ｲｸﾀ ｸﾙｰﾄﾞﾌﾛｰﾘﾝｸﾞ ※ｼﾞｮｲﾝﾄｼｰﾙ施工 | F49: 3 | G49: 坪 | H49: 20000 | I49: 14000 | J49: 0 | P49: 基本 | Q49: 1 | R49: 10.7653 | S49: 【床 面積 (全階 洗面所)】+【床 面積 (全階 脱衣室)】+【床 面積 (全階 便所)】 | T49: 7.4529000+0.0000000+3.3124000
A50: 22 | B50: 23 | C50: 1 | D50: 【ALL金物工法】木造構造材･羽柄材･ﾌﾟﾚｶｯﾄ | E50: 基本 本体+付帯 | F50: 35.51 | G50: 坪 | H50: 102900 | I50: 72000 | J50: 0 | P50: 基本 | Q50: 1 | R50: 117.37 | S50: IF(【施工床面積[ﾄｰﾀﾙ面積表]】,【施工床面積[ﾄｰﾀﾙ面積表]】,【部屋(全階) 面積】+【バルコニー 面積(壁芯)】+【ポーチ 面積】) | T50: IF(117.3700000,117.3700000,115.3130000+0.0000000+2.6109000)
A51: 22 | B51: 24 | C51: 1 | D51: 金物費捻出 | F51: -1 | G51: 式 | H51: 85800 | I51: 60000 | J51: 0 | P51: 基本 | Q51: 1 | R51: -1
A52: 22 | B52: 25 | C52: 1 | D52: 割増A：建物難易度 | E52: 外部入隅の数 | F52: 4 | G52: ヶ所 | H52: 21500 | I52: 15000 | J52: 0 | P52: 基本 | Q52: 1 | R52: 4 | S52: 【外壁入隅(全階) ヶ所数】 | T52: 4.0000000
A53: 22 | B53: 26 | C53: 1 | D53: 割増B：2階比 | E53: 1階-2階 | F53: 1.06 | G53: 坪 | H53: 3600 | I53: 2500 | J53: 0 | P53: 基本 | Q53: 1 | R53: 3.52 | S53: 評価式1 ≧ 評価式2 | T53: 59.4100000-55.8900000
A54: 22 | B54: 27 | C54: 1 | D54: 化粧柱 | E54: 化粧柱[個数] | F54: 1 | G54: 本 | H54: 17200 | I54: 12000 | J54: 0 | P54: 積算ｼﾝﾎﾞﾙ | Q54: 1 | R54: 1
A55: 22 | B55: 28 | C55: 1 | D55: 金物費 | F55: 1 | G55: 式 | H55: 85800 | I55: 60000 | J55: 0 | P55: 基本 | Q55: 1 | R55: 1
A56: 22 | B56: 29 | C56: 1 | D56: 遠方割増 | E56: 都度計算 ※西尾市、該当なし | F56: 1 | G56: 式 | H56: 0 | I56: 0 | J56: 0 | K56: ☆彡 | P56: 基本 | Q56: 1 | R56: 1
A57: 22 | B57: 30 | C57: 1 | D57: 構造追加費 | E57: 基本の5％ﾍﾞｰｽ | F57: 1 | G57: 式 | H57: 182800 | I57: 127900 | J57: 0 | P57: 基本 | Q57: 1 | R57: 1
A58: 31 | B58: 32 | C58: 1 | D58: 下地材 | E58: 基本 | F58: 35.51 | G58: 坪 | H58: 37200 | I58: 26000 | J58: 0 | P58: 基本 | Q58: 1 | R58: 117.37 | S58: IF(【施工床面積[ﾄｰﾀﾙ面積表]】,【施工床面積[ﾄｰﾀﾙ面積表]】,【施工床(全階) 面積】+【ポーチ 面積】) | T58: IF(117.3700000,117.3700000,117.3832000+2.6109000)
A59: 31 | B59: 33 | C59: 1 | D59: 下地材(割増) | E59: 入隅ヶ所数 | F59: 4 | G59: ヶ所 | H59: 14300 | I59: 10000 | J59: 0 | P59: 基本 | Q59: 1 | R59: 4 | S59: 【外壁入隅(全階) ヶ所数】 | T59: 4.0000000
A60: 31 | B60: 34 | C60: 1 | D60: 軒天無し | E60: ｱｽﾉﾝ8㎜ 無塗装板 | F60: 1 | G60: 式 | H60: -14300 | I60: -10000 | J60: 0 | P60: 基本 | Q60: 1 | R60: 1
A61: 31 | B61: 35 | C61: 1 | D61: 養生費・補修費捻出 | F61: 1 | G61: 式 | H61: -142900 | I61: -100000 | J61: 0 | P61: 基本 | Q61: 1 | R61: 1
A62: 31 | B62: 36 | C62: 1 | D62: 玄関框 | E62: ﾌﾟﾚｲﾘｰﾎｰﾑｽﾞｽﾏｰﾄ框 | F62: 1 | G62: 本 | H62: 14300 | I62: 10000 | J62: 0 | O62: ｶﾏﾁ長さから集計 | P62: 基本 | Q62: 1 | R62: 4.568 | S62: 【カマチ(全階) 長】 | T62: 4.5680000
A63: 31 | B63: 37 | C63: 1 | D63: 上框(挽板･無垢床用) | E63: W6尺 床合わせ面材貼り | F63: 2 | G63: 本 | H63: 18600 | I63: 13000 | J63: 0 | P63: 基本 | Q63: 1 | R63: 0
A64: 31 | B64: 38 | C64: 1 | D64: 床組無し(内部土間床) | E64: 内部土間床･ｲﾝﾅｰｶﾞﾚｰｼﾞ･外部収納等 | F64: 5.59 | G64: ㎡ | H64: -2900 | I64: -2000 | J64: 0 | P64: 基本 | Q64: 1 | R64: 5.5897 | S64: 【床 面積 (1階 車庫等)】+【床 面積 (1階 外部部屋)】+【床 面積 (1階 玄関)】 | T64: 0.0000000+0.0000000+5.5897000
A65: 31 | B65: 39 | C65: 1 | D65: 階段(1～2階) | E65: 標準箱型6段回り以下 | F65: 1 | G65: ｾｯﾄ | H65: 151500 | I65: 106000 | J65: 0 | P65: 基本 | Q65: 1 | R65: 1 | S65: 【部屋 数 (1階 階段室)】 | T65: 1.0000000
A66: 31 | B66: 40 | C66: 1 | D66: 階段手摺 | E66: 丸棒手摺（金具ｶﾜｼﾞｭﾝ） | F66: 1 | G66: ｾｯﾄ | H66: 43500 | I66: 30400 | J66: 0 | P66: 基本 | Q66: 1 | R66: 1 | S66: 【部屋 数 (1階 階段室)】+【部屋 数 (3階 階段室)】+【部屋 数 (R階 階段室)】 | T66: 1.0000000+0.0000000+0.0000000
A67: 31 | B67: 41 | C67: 1 | D67: 枕棚+ﾊﾟｲﾌﾟ | E67: W6尺以下 | F67: 6 | G67: ヶ所 | H67: 17200 | I67: 12000 | J67: 0 | P67: 基本 | Q67: 1 | R67: 6 | S67: 【ハンガーパイプ 枕段 ヶ所数】 | T67: 6.0000000
A68: 31 | B68: 42 | C68: 1 | D68: 下地補強 | F68: 3 | G68: ヶ所 | H68: 28600 | I68: 20000 | J68: 0 | P68: 基本 | Q68: 1 | R68: 0
A69: 31 | B69: 43 | C69: 1 | D69: 笠木 | E69: ｺﾞﾑ集成材 ｳﾚﾀﾝ塗装 | F69: 2 | G69: 本 | H69: 20000 | I69: 14000 | J69: 0 | O69: 笠木長+手摺(内部)長さから集計 | P69: 基本 | Q69: 1 | R69: 4.203 | S69: 【笠木長(全階)】-【外部笠木(全階) 長】+【手摺(内部) 長】 | T69: 4.2030000-0.0000000+0.0000000
A70: 31 | B70: 44 | C70: 1 | D70: 大壁和室造作材 | E70: 付鴨居無し | F70: 2.69 | G70: ㎡ | H70: 8600 | I70: 6000 | J70: 0 | P70: 基本 | Q70: 1 | R70: 2.6913 | S70: 【部屋面積 (全階 和室)】 | T70: 2.6913000
A71: 31 | B71: 45 | C71: 1 | D71: 床上げ用材料（框別） | F71: 2.69 | G71: ㎡ | H71: 8600 | I71: 6000 | J71: 0 | P71: 基本 | Q71: 1 | R71: 0
A72: 31 | B72: 46 | C72: 1 | D72: 中段・枕棚ｾｯﾄ | E72: W6尺以下 | F72: 1 | G72: ヶ所 | H72: 22900 | I72: 16000 | J72: 0 | P72: 基本 | Q72: 1 | R72: 1 | S72: 【押入段 中段・枕段 ヶ所数】 | T72: 1.0000000
A73: 31 | B73: 47 | C73: 1 | D73: 鋼板屋根遮音下地 | E73: ﾋﾞﾙﾎﾞｰﾄﾞ9㎜ | F73: 96.01 | G73: ㎡ | H73: 1100 | I73: 750 | J73: 0 | P73: 基本 | Q73: 1 | R73: 96.006 | S73: 【屋根面積】 | T73: 96.0060000
A74: 31 | B74: 48 | C74: 1 | D74: 外壁透湿防水シート | E74: ﾀｲﾍﾞｯｸ（ﾄﾞﾚｲﾝﾗｯﾌﾟ又はﾊｳｽﾗｯﾌﾟ） | F74: 193.53 | G74: ㎡ | H74: 800 | I74: 500 | J74: 0 | P74: 基本 | Q74: 1 | R74: 193.5295 | S74: 【妻壁 面積(軒天考慮)】+【手摺(外部) 面積】+【外壁腰壁 面積】+【外壁 面積(軒天考慮)】 | T74: 0.9237000+0.0000000+0.0000000+192.6058000
A75: 31 | B75: 49 | C75: 1 | D75: 耐力面材 | E75: ﾀﾞｲﾗｲﾄ MS9 | F75: 87 | G75: 枚 | H75: 4300 | I75: 3000 | J75: 0 | O75: 外壁面積から集計 | P75: 基本 | Q75: 1 | R75: 86.6171 | S75: (【外壁(全階) 面積】+【外断熱外壁腰壁(全階) 面積】+【妻壁 面積】+【手摺(外部) 面積】)*1.15/2.73 | T75: (204.4095000+0.0000000+1.2119000+0.0000000)*1.15/2.73
A76: 31 | B76: 50 | C76: 1 | D76: 制震ﾀﾞﾝﾊﾟｰ | E76: MIRAIE | F76: 4 | G76: 本 | H76: 86500 | I76: 60500 | J76: 0 | P76: 基本 | Q76: 1 | R76: 4 | S76: 評価式1 ≦ 評価式2 | T76: 4
A77: 31 | B77: 51 | C77: 1 | D77: 窓枠(掃出し3方､中連4方) | E77: LIXIL ﾗｼｯｻS ｽﾏｰﾄ10 | F77: 12 | G77: 本 | H77: 4200 | I77: 2900 | J77: 0 | O77: 外部戸の左右+幅長さ､外部窓の上下左右長さ | P77: 基本 | Q77: 1 | R77: 44.712 | S77: 【金窓(外部) (上+左+右)枠長】+【金窓(外部) 下枠長】+【金戸(外部) (上+左+右)枠長】+【金戸(外部) 下枠長】 | T77: 21.7950000+10.2150000+12.7020000+0.0000000
A78: 31 | B78: 52 | C78: 1 | D78: 化粧巾木 | E78: LIXIL ﾗｲﾝ巾木 | F78: 37 | G78: 本 | H78: 2100 | I78: 1450 | J78: 0 | O78: 立体ﾃﾞｰﾀから集計(巾木長) | P78: 巾木仕上(m) | Q78: 1 | R78: 116.8733
A79: 31 | B79: 53 | C79: 1 | D79: ﾆｯﾁ | E79: 材工+ｸﾛｽ | F79: 1 | G79: ヶ所 | H79: 25800 | I79: 18000 | J79: 0 | P79: 積算ｼﾝﾎﾞﾙ | Q79: 1 | R79: 1
A80: 31 | B80: 54 | C80: 1 | D80: FB手摺りﾊｰﾌ×0.5 | E80: FB手すりﾊｰﾌ[個数] | F80: 1 | G80: ｾｯﾄ | H80: 176000 | I80: 123200 | J80: 0 | P80: 積算ｼﾝﾎﾞﾙ | Q80: 1 | R80: 1
A81: 31 | B81: 55 | C81: 1 | D81: 換気部材（一般用・破風レス対応） | E81: 軒+ケラバ長さ換算追加 | F81: 55.61 | G81: ｍ | H81: 2200 | I81: 1500 | J81: 0 | P81: 基本 | Q81: 1 | R81: 55.611 | S81: (1-【特長-条件０２】)*(【屋根(木造) 屋根線(軒先) 長】+【屋根(木造) 屋根線(けらば) 長】) | T81: (1-0.0000000)*(29.8160000+25.7950000)
A82: 31 | B82: 56 | C82: 1 | D82: 床ｶﾞﾗﾘ変更 | E82: 樹脂→オーク無垢（無塗装） | F82: 6 | G82: ヶ所 | H82: 0 | I82: 0 | J82: 0 | P82: 基本 | Q82: 1 | R82: 6
A83: 31 | B83: 57 | C83: 1 | D83: 床ｶﾞﾗﾘ変更 | E83: 塗装費のみ | F83: 1 | G83: 式 | H83: 29000 | I83: 20300 | J83: 0 | P83: 基本 | Q83: 1 | R83: 1
A84: 31 | B84: 58 | C84: 1 | D84: アーチ垂れ壁 3尺 室内 | E84: 材工+ｸﾛｽ | F84: 1 | G84: ヶ所 | H84: 50000 | I84: 35000 | J84: 0 | P84: 積算ｼﾝﾎﾞﾙ | Q84: 1 | R84: 1
A85: 31 | B85: 59 | C85: 1 | D85: 小屋裏耐力面材：屋根勾配3寸超6寸未満 | E85: ダイライトMS9片面張 | F85: 1 | G85: 式 | H85: 57200 | I85: 40000 | J85: 0 | K85: ☆彡 | P85: 基本 | Q85: 1 | R85: 1
A86: 31 | B86: 60 | C86: 1 | D86: 床養生費 | F86: 1 | G86: 式 | H86: 71500 | I86: 50000 | J86: 0 | P86: 基本 | Q86: 1 | R86: 1
A87: 31 | B87: 61 | C87: 1 | D87: 補修費 | F87: 1 | G87: 式 | H87: 71500 | I87: 50000 | J87: 0 | P87: 基本 | Q87: 1 | R87: 1
A88: 31 | B88: 62 | C88: 1 | D88: LDK下がり天井造作下地材 | F88: 5.46 | G88: ｍ | H88: 7200 | I88: 5000 | J88: 0 | P88: 基本 | Q88: 1 | R88: 1
A89: 31 | B89: 63 | C89: 1 | D89: 垂れ壁 水平 | E89: 3尺 クロス仕上 | F89: 1 | G89: ヶ所 | H89: 11500 | I89: 8000 | J89: 0 | P89: 積算ｼﾝﾎﾞﾙ | Q89: 1 | R89: 1
A90: 31 | B90: 64 | C90: 1 | D90: 床ﾌﾛｱﾀｲﾙ下地 合板 | E90: 910×1820 12㎜ | F90: 6 | G90: 枚 | H90: 1900 | I90: 1300 | J90: 0 | P90: 基本 | Q90: 1 | R90: 1
A91: 31 | B91: 65 | C91: 1 | D91: 床見切 | F91: 1 | G91: 本 | H91: 7200 | I91: 5000 | J91: 0 | P91: 基本 | Q91: 1 | R91: 1
A92: 31 | B92: 66 | C92: 1 | D92: ﾌﾛｱﾀｲﾙ面積調整分 | E92: 契変①で+1㎡ | F92: 1 | G92: 式 | H92: 14300 | I92: 10000 | J92: 0 | P92: 基本 | Q92: 1 | R92: 1
A93: 31 | B93: 67 | C93: 1 | D93: 縦格子 | E93: 材工 参考（DAIKEN 縦格子ﾕﾆｯﾄ） | F93: 1 | G93: ヶ所 | H93: 160000 | I93: 112000 | J93: 0 | P93: 積算ｼﾝﾎﾞﾙ | Q93: 1 | R93: 1
A94: 31 | B94: 68 | C94: 1 | D94: 標準外工事 | E94: 横引き延長配管 | F94: 2 | G94: ｍ | H94: 2900 | I94: 2000 | J94: 0 | P94: 基本 | Q94: 1 | R94: 1
A95: 31 | B95: 69 | C95: 1 | D95: 標準外工事 | E95: 曲がり1カ所 | F95: 1 | G95: ヶ所 | H95: 2900 | I95: 2000 | J95: 0 | P95: 基本 | Q95: 1 | R95: 1
A96: 31 | B96: 70 | C96: 1 | D96: ししまるくんﾇｯｸｽﾍﾟｰｽ造作追加 | E96: 材工 | F96: 1 | G96: 式 | H96: 57200 | I96: 40000 | J96: 0 | P96: 基本 | Q96: 1 | R96: 1
A97: 31 | B97: 71 | C97: 1 | D97: ﾗﾝﾄﾞﾘｰﾛｰﾌﾟ | E97: KAWAJUN SE-149-SC ﾎﾜｲﾄ | F97: 1 | G97: ｾｯﾄ | H97: 15800 | I97: 11000 | J97: 0 | P97: 基本 | Q97: 1 | R97: 1
A98: 31 | B98: 72 | C98: 1 | D98: ﾗﾝﾄﾞﾘｰﾛｰﾌﾟ施工費 | E98: KAWAJUN SE-149-SC ﾎﾜｲﾄ | F98: 1 | G98: 式 | H98: 4300 | I98: 3000 | J98: 0 | P98: 基本 | Q98: 1 | R98: 1
A99: 31 | B99: 73 | C99: 1 | D99: 天井埋込ｶｰﾃﾝBOX造作 | E99: W2700 | F99: 1 | G99: ヶ所 | H99: 27500 | I99: 19200 | J99: 0 | P99: 積算ｼﾝﾎﾞﾙ | Q99: 1 | R99: 1
A100: 31 | B100: 74 | C100: 1 | D100: ﾄｲﾚ壁ﾆｯﾁ | E100: 材工 | F100: 1 | G100: ヶ所 | H100: 22900 | I100: 16000 | J100: 0 | P100: 積算ｼﾝﾎﾞﾙ | Q100: 1 | R100: 1
A101: 31 | B101: 75 | C101: 1 | D101: ●33調整分 | F101: 1 | G101: 式 | H101: 475000 | I101: 0 | J101: 0 | P101: 基本 | Q101: 1 | R101: 1
A102: 31 | B102: 76 | C102: 1 | D102: 電気設備用点検口 | E102: 300角 材工 | F102: 1 | G102: 個 | H102: 17200 | I102: 12000 | J102: 0 | P102: 基本 | Q102: 1 | R102: 1
A103: 77 | B103: 78 | C103: 1 | D103: 基本手間 | E103: 【ALL金物工法】 | F103: 34.88 | G103: 坪 | H103: 42900 | I103: 30000 | J103: 0 | O103: 施工床面積 | P103: 基本 | Q103: 1 | R103: 115.3 | S103: IF(【延床面積[ﾄｰﾀﾙ面積表]】,【延床面積[ﾄｰﾀﾙ面積表]】,(【部屋(全階) 面積】)) | T103: IF(115.3000000,115.3000000,(115.3130000))
A104: 77 | B104: 79 | C104: 1 | D104: 外周入隅（玄関は基本に含む・袖壁は必要） | F104: 4 | G104: ヶ所 | H104: 7200 | I104: 5000 | J104: 0 | P104: 基本 | Q104: 1 | R104: 4 | S104: 【外壁入隅(全階) ヶ所数】 | T104: 4.0000000
A105: 77 | B105: 80 | C105: 1 | D105: ﾍﾞﾗﾝﾀﾞ･ﾎﾟｰﾁ･ﾃﾗｽ | F105: 2.07 | G105: ㎡ | H105: 8600 | I105: 6000 | J105: 0 | P105: 基本 | Q105: 1 | R105: 2.07 | S105: 【施工床面積[ﾄｰﾀﾙ面積表]】-【延床面積[ﾄｰﾀﾙ面積表]】-【部屋面積 (全階 吹抜)】 | T105: 117.3700000-115.3000000-0.0000000
A106: 77 | B106: 81 | C106: 1 | D106: 新ﾃﾝﾌﾟﾚｰﾄ用調整費 | F106: 1 | G106: 式 | H106: 142900 | I106: 100000 | J106: 0 | P106: 基本 | Q106: 1 | R106: 0
A107: 77 | B107: 82 | C107: 1 | D107: 片引き戸造作手間 | F107: 3 | G107: ヶ所 | H107: 15800 | I107: 11000 | J107: 0 | P107: 基本 | Q107: 1 | R107: 3
A108: 77 | B108: 83 | C108: 1 | D108: 下屋 | E108: 床㎡(1階-2階) 6寸未満 | F108: 3.52 | G108: ㎡ | H108: 2900 | I108: 2000 | J108: 0 | P108: 基本 | Q108: 1 | R108: 3.52 | S108: 評価式1 ≧ 評価式2 | T108: 59.4100000-55.8900000
...

Sheet 条件
D4: 1ページあたりの明細数 | E4: 20
D5: ※大きい数字を設定しても必ずしも１ページがその行数になるとは限りません。
D7: 合計書式 | E7: 合計
M8: 【構造】 | Q8: 【契約・契約後変更】
D9: 表紙用物件情報 | M9: 木造軸組み一般構造 | Q9: 契約
D10: 表紙工事名称 | E10: 古居 徹朗 様・古居 百恵 様邸新築工事⑦ | G10: 会社名 | M10: 木造軸組みマイホーム構造 | Q10: 契約後変更
D11: 表紙工事場所 | E11: 西尾市戸ケ崎 | G11: 会社事業所名
D12: 表紙工事種別 | E12: 新築 | G12: 会社郵便番号
D13: 表紙施主氏名 | E13: 古居 徹朗 様・古居 百恵 | G13: 会社住所１
D14: 表紙延床面積 | E14: 115.3 | F14: ㎡ | G14: 会社住所２
E15: 34.87 | F15: 坪 | G15: 会社TEL
D16: 金額計算まるめ | E16: 切り捨て | G16: 会社FAX
D17: 表紙見積金額合計 | E17: =明細書!$G$41 -> 35971100 | G17: 会社URL
D18: 表紙消費税 | E18: =明細書!$G$27 -> 3270100 | G18: 会社MAIL
G19: 工事概要 | H19: 木造軸組ALL金物構造
G20: 図面日付 | H20: 45942
D21: 消費税 | G21: プラン名 | H21: ⑦ 自由設計プラン
D22: 消費税書式 | E22: 消費税等
D23: 消費税税率 | E23: 10 | F23: %
D24: 消費税まるめ | E24: 切り捨て
D26: 経費行 | G26: 見積番号 | H26: 25-2507(13)-H230堀-NO-FT⑦04B | M26: 【見積番号】 | O26: （例）24-2311(05)-024堀-AJ-NR①01
D27: 経費行書式 | E27: 経費行 | G27: 提出日 | H27: 45955 | M27: 24年作成-どのﾃﾝﾌﾟﾚｰﾄか※ﾃﾝﾌﾟﾚｰﾄの日付（ﾃﾝﾌﾟﾚｰﾄ番号）-24年の何番目に作成（〇は営業の苗字の一番目）-建築地（安城ならAJ）-△施主様の苗字の一文字目□施主様の名前の一文字目①（図面番号）01（何回目の本見積か）
G28: 契約・契約後変更 | H28: 契約後変更 | M28: 【提出日】
M29: 見積を提出した日
G30: ※各条件を変更した結果を反映する場合には 明細書再構築を行う必要があります。 表紙・明細書が強制的に再構成されます。

Sheet 粗利表
B1: 粗利管理表 | F1: 作成日： | G1: 45955 | H1: 担当： | I1: 川澄
A2: № | B2: 名称 | C2: 摘要 | D2: 数量 | E2: 単位 | F2: 見積単価 | G2: 設計原価 | H2: 粗利額 | I2: 粗利率
A3: 1 | B3: =VLOOKUP(0,データ!$A2:$I$32,4,FALSE) -> 仮設工事 | C3: =VLOOKUP(0,データ!$A2:$I$32,5,FALSE) -> 0 | D3: =VLOOKUP(0,データ!$A2:$I$32,6,FALSE) -> 1 | E3: =VLOOKUP(0,データ!$A2:$I$32,7,FALSE) -> 式 | F3: =VLOOKUP(0,データ!$A2:$I$32,8,FALSE) -> 914151 | G3: =VLOOKUP(0,データ!$A2:$I$32,9,FALSE) -> 625715 | H3: =F3-G3 -> 288436 | I3: =ROUND(H3/F3,3) -> 0.316 | L3: 【操作方法】
A4: 2 | B4: =VLOOKUP(0,データ!$A3:$I$32,4,FALSE) -> 基礎工事 | C4: =VLOOKUP(0,データ!$A3:$I$32,5,FALSE) -> 0 | D4: =VLOOKUP(0,データ!$A3:$I$32,6,FALSE) -> 1 | E4: =VLOOKUP(0,データ!$A3:$I$32,7,FALSE) -> 式 | F4: =VLOOKUP(0,データ!$A3:$I$32,8,FALSE) -> 2275605 | G4: =VLOOKUP(0,データ!$A3:$I$32,9,FALSE) -> 1588963 | H4: =F4-G4 -> 686642 | I4: =ROUND(H4/F4,3) -> 0.302 | K4: 1 | L4: エラー行（＃N/A)を削除
A5: 3 | B5: =VLOOKUP(0,データ!$A4:$I$32,4,FALSE) -> 木工事 | C5: =VLOOKUP(0,データ!$A4:$I$32,5,FALSE) -> 0 | D5: =VLOOKUP(0,データ!$A4:$I$32,6,FALSE) -> 1 | E5: =VLOOKUP(0,データ!$A4:$I$32,7,FALSE) -> 式 | F5: =VLOOKUP(0,データ!$A4:$I$32,8,FALSE) -> 12317611 | G5: =VLOOKUP(0,データ!$A4:$I$32,9,FALSE) -> 7910157 | H5: =F5-G5 -> 4407454 | I5: =ROUND(H5/F5,3) -> 0.358 | K5: 2 | L5: 諸経費金額を入力（又は計算式）
A6: 4 | B6: =VLOOKUP(0,データ!$A5:$I$32,4,FALSE) -> 断熱工事 | C6: =VLOOKUP(0,データ!$A5:$I$32,5,FALSE) -> 0 | D6: =VLOOKUP(0,データ!$A5:$I$32,6,FALSE) -> 1 | E6: =VLOOKUP(0,データ!$A5:$I$32,7,FALSE) -> 式 | F6: =VLOOKUP(0,データ!$A5:$I$32,8,FALSE) -> 1256721 | G6: =VLOOKUP(0,データ!$A5:$I$32,9,FALSE) -> 871719 | H6: =F6-G6 -> 385002 | I6: =ROUND(H6/F6,3) -> 0.306 | K6: 3 | L6: 右下の情報欄を記入
A7: 5 | B7: =VLOOKUP(0,データ!$A6:$I$32,4,FALSE) -> 屋根工事 | C7: =VLOOKUP(0,データ!$A6:$I$32,5,FALSE) -> 0 | D7: =VLOOKUP(0,データ!$A6:$I$32,6,FALSE) -> 1 | E7: =VLOOKUP(0,データ!$A6:$I$32,7,FALSE) -> 式 | F7: =VLOOKUP(0,データ!$A6:$I$32,8,FALSE) -> 739277 | G7: =VLOOKUP(0,データ!$A6:$I$32,9,FALSE) -> 513653 | H7: =F7-G7 -> 225624 | I7: =ROUND(H7/F7,3) -> 0.305 | K7: 4 | L7: 必要に応じて、捺印欄も文字や印影画像入力可能
A8: 6 | B8: =VLOOKUP(0,データ!$A7:$I$32,4,FALSE) -> 板金・樋工事 | C8: =VLOOKUP(0,データ!$A7:$I$32,5,FALSE) -> 0 | D8: =VLOOKUP(0,データ!$A7:$I$32,6,FALSE) -> 1 | E8: =VLOOKUP(0,データ!$A7:$I$32,7,FALSE) -> 式 | F8: =VLOOKUP(0,データ!$A7:$I$32,8,FALSE) -> 202780 | G8: =VLOOKUP(0,データ!$A7:$I$32,9,FALSE) -> 141496 | H8: =F8-G8 -> 61284 | I8: =ROUND(H8/F8,3) -> 0.302 | K8: 5 | L8: PDFで印刷
A9: 7 | B9: =VLOOKUP(0,データ!$A8:$I$32,4,FALSE) -> 外部建具工事 | C9: =VLOOKUP(0,データ!$A8:$I$32,5,FALSE) -> 0 | D9: =VLOOKUP(0,データ!$A8:$I$32,6,FALSE) -> 1 | E9: =VLOOKUP(0,データ!$A8:$I$32,7,FALSE) -> 式 | F9: =VLOOKUP(0,データ!$A8:$I$32,8,FALSE) -> 981800 | G9: =VLOOKUP(0,データ!$A8:$I$32,9,FALSE) -> 687000 | H9: =F9-G9 -> 294800 | I9: =ROUND(H9/F9,3) -> 0.3
A10: 8 | B10: =VLOOKUP(0,データ!$A9:$I$32,4,FALSE) -> 内部建具工事 | C10: =VLOOKUP(0,データ!$A9:$I$32,5,FALSE) -> 0 | D10: =VLOOKUP(0,データ!$A9:$I$32,6,FALSE) -> 1 | E10: =VLOOKUP(0,データ!$A9:$I$32,7,FALSE) -> 式 | F10: =VLOOKUP(0,データ!$A9:$I$32,8,FALSE) -> 1133700 | G10: =VLOOKUP(0,データ!$A9:$I$32,9,FALSE) -> 792920 | H10: =F10-G10 -> 340780 | I10: =ROUND(H10/F10,3) -> 0.301
A11: 9 | B11: =VLOOKUP(0,データ!$A10:$I$32,4,FALSE) -> 外装工事 | C11: =VLOOKUP(0,データ!$A10:$I$32,5,FALSE) -> 0 | D11: =VLOOKUP(0,データ!$A10:$I$32,6,FALSE) -> 1 | E11: =VLOOKUP(0,データ!$A10:$I$32,7,FALSE) -> 式 | F11: =VLOOKUP(0,データ!$A10:$I$32,8,FALSE) -> 2087931 | G11: =VLOOKUP(0,データ!$A10:$I$32,9,FALSE) -> 1449077 | H11: =F11-G11 -> 638854 | I11: =ROUND(H11/F11,3) -> 0.306
A12: 10 | B12: =VLOOKUP(0,データ!$A11:$I$32,4,FALSE) -> 左官工事 | C12: =VLOOKUP(0,データ!$A11:$I$32,5,FALSE) -> 0 | D12: =VLOOKUP(0,データ!$A11:$I$32,6,FALSE) -> 1 | E12: =VLOOKUP(0,データ!$A11:$I$32,7,FALSE) -> 式 | F12: =VLOOKUP(0,データ!$A11:$I$32,8,FALSE) -> 254156 | G12: =VLOOKUP(0,データ!$A11:$I$32,9,FALSE) -> 176780 | H12: =F12-G12 -> 77376 | I12: =ROUND(H12/F12,3) -> 0.304
A13: 11 | B13: =VLOOKUP(0,データ!$A12:$I$32,4,FALSE) -> タイル工事 | C13: =VLOOKUP(0,データ!$A12:$I$32,5,FALSE) -> 0 | D13: =VLOOKUP(0,データ!$A12:$I$32,6,FALSE) -> 1 | E13: =VLOOKUP(0,データ!$A12:$I$32,7,FALSE) -> 式 | F13: =VLOOKUP(0,データ!$A12:$I$32,8,FALSE) -> 254760 | G13: =VLOOKUP(0,データ!$A12:$I$32,9,FALSE) -> 177868 | H13: =F13-G13 -> 76892 | I13: =ROUND(H13/F13,3) -> 0.302
A14: 12 | B14: =VLOOKUP(0,データ!$A13:$I$32,4,FALSE) -> 塗装工事 | C14: =VLOOKUP(0,データ!$A13:$I$32,5,FALSE) -> 0 | D14: =VLOOKUP(0,データ!$A13:$I$32,6,FALSE) -> 1 | E14: =VLOOKUP(0,データ!$A13:$I$32,7,FALSE) -> 式 | F14: =VLOOKUP(0,データ!$A13:$I$32,8,FALSE) -> 42900 | G14: =VLOOKUP(0,データ!$A13:$I$32,9,FALSE) -> 30000 | H14: =F14-G14 -> 12900 | I14: =ROUND(H14/F14,3) -> 0.301
A15: 13 | B15: =VLOOKUP(0,データ!$A14:$I$32,4,FALSE) -> 内装工事 | C15: =VLOOKUP(0,データ!$A14:$I$32,5,FALSE) -> 0 | D15: =VLOOKUP(0,データ!$A14:$I$32,6,FALSE) -> 1 | E15: =VLOOKUP(0,データ!$A14:$I$32,7,FALSE) -> 式 | F15: =VLOOKUP(0,データ!$A14:$I$32,8,FALSE) -> 896446 | G15: =VLOOKUP(0,データ!$A14:$I$32,9,FALSE) -> 625684 | H15: =F15-G15 -> 270762 | I15: =ROUND(H15/F15,3) -> 0.302
A16: 14 | B16: =VLOOKUP(0,データ!$A15:$I$32,4,FALSE) -> 住宅設備機器工事 | C16: =VLOOKUP(0,データ!$A15:$I$32,5,FALSE) -> 0 | D16: =VLOOKUP(0,データ!$A15:$I$32,6,FALSE) -> 1 | E16: =VLOOKUP(0,データ!$A15:$I$32,7,FALSE) -> 式 | F16: =VLOOKUP(0,データ!$A15:$I$32,8,FALSE) -> 2340500 | G16: =VLOOKUP(0,データ!$A15:$I$32,9,FALSE) -> 1637950 | H16: =F16-G16 -> 702550 | I16: =ROUND(H16/F16,3) -> 0.3
A17: 15 | B17: =VLOOKUP(0,データ!$A16:$I$32,4,FALSE) -> 給排水設備工事 | C17: =VLOOKUP(0,データ!$A16:$I$32,5,FALSE) -> 0 | D17: =VLOOKUP(0,データ!$A16:$I$32,6,FALSE) -> 1 | E17: =VLOOKUP(0,データ!$A16:$I$32,7,FALSE) -> 式 | F17: =VLOOKUP(0,データ!$A16:$I$32,8,FALSE) -> 242900 | G17: =VLOOKUP(0,データ!$A16:$I$32,9,FALSE) -> 170000 | H17: =F17-G17 -> 72900 | I17: =ROUND(H17/F17,3) -> 0.3
A18: 16 | B18: =VLOOKUP(0,データ!$A17:$I$32,4,FALSE) -> 電気設備工事 | C18: =VLOOKUP(0,データ!$A17:$I$32,5,FALSE) -> 0 | D18: =VLOOKUP(0,データ!$A17:$I$32,6,FALSE) -> 1 | E18: =VLOOKUP(0,データ!$A17:$I$32,7,FALSE) -> 式 | F18: =VLOOKUP(0,データ!$A17:$I$32,8,FALSE) -> 1243650 | G18: =VLOOKUP(0,データ!$A17:$I$32,9,FALSE) -> 866060 | H18: =F18-G18 -> 377590 | I18: =ROUND(H18/F18,3) -> 0.304
A19: 17 | B19: =VLOOKUP(0,データ!$A18:$I$32,4,FALSE) -> 換気システム工事 | C19: =VLOOKUP(0,データ!$A18:$I$32,5,FALSE) -> 0 | D19: =VLOOKUP(0,データ!$A18:$I$32,6,FALSE) -> 1 | E19: =VLOOKUP(0,データ!$A18:$I$32,7,FALSE) -> 式 | F19: =VLOOKUP(0,データ!$A18:$I$32,8,FALSE) -> 472052 | G19: =VLOOKUP(0,データ!$A18:$I$32,9,FALSE) -> 330156 | H19: =F19-G19 -> 141896 | I19: =ROUND(H19/F19,3) -> 0.301
A20: 18 | B20: =VLOOKUP(0,データ!$A19:$I$32,4,FALSE) -> エアコン工事 | C20: =VLOOKUP(0,データ!$A19:$I$32,5,FALSE) -> 0 | D20: =VLOOKUP(0,データ!$A19:$I$32,6,FALSE) -> 1 | E20: =VLOOKUP(0,データ!$A19:$I$32,7,FALSE) -> 式 | F20: =VLOOKUP(0,データ!$A19:$I$32,8,FALSE) -> 351500 | G20: =VLOOKUP(0,データ!$A19:$I$32,9,FALSE) -> 245000 | H20: =F20-G20 -> 106500 | I20: =ROUND(H20/F20,3) -> 0.303
... A23: 21 | B23: =VLOOKUP(0,データ!$A22:$I$32,4,FALSE) -> 雑工事 | C23: =VLOOKUP(0,データ!$A22:$I$32,5,FALSE) -> 0 | D23: =VLOOKUP(0,データ!$A22:$I$32,6,FALSE) -> 1 | E23: =VLOOKUP(0,データ!$A22:$I$32,7,FALSE) -> 式 | F23: =VLOOKUP(0,データ!$A22:$I$32,8,FALSE) -> 160385 | G23: =VLOOKUP(0,データ!$A22:$I$32,9,FALSE) -> 111543 | H23: =F23-G23 -> 48842 | I23: =ROUND(H23/F23,3) -> 0.305
A24: 22 | B24: 管理費 | C24: =VLOOKUP(0,データ!$A23:$I$32,5,FALSE) -> 0 | D24: =VLOOKUP(0,データ!$A23:$I$32,6,FALSE) -> 1 | E24: =VLOOKUP(0,データ!$A23:$I$32,7,FALSE) -> 0 | F24: =SUM(F3:F23)*0.03-1 -> 876230.75 | G24: =SUM(G3:G23)*0.02 -> 393577.82 | H24: =F24-G24 -> 482652.93 | I24: =ROUND(H24/F24,3) -> 0.551
A25: 23 | B25: =VLOOKUP(0,データ!$A24:$I$32,4,FALSE) -> 屋外付帯工事 | C25: =VLOOKUP(0,データ!$A24:$I$32,5,FALSE) -> 0 | D25: =VLOOKUP(0,データ!$A24:$I$32,6,FALSE) -> 1 | E25: =VLOOKUP(0,データ!$A24:$I$32,7,FALSE) -> 式 | F25: =VLOOKUP(0,データ!$A24:$I$32,8,FALSE) -> 1347250 | G25: =VLOOKUP(0,データ!$A24:$I$32,9,FALSE) -> 927282 | H25: =F25-G25 -> 419968 | I25: =ROUND(H25/F25,3) -> 0.312
A26: 24 | B26: =VLOOKUP(0,データ!$A25:$I$32,4,FALSE) -> 諸費用 | C26: =VLOOKUP(0,データ!$A25:$I$32,5,FALSE) -> 0 | D26: =VLOOKUP(0,データ!$A25:$I$32,6,FALSE) -> 1 | E26: =VLOOKUP(0,データ!$A25:$I$32,7,FALSE) -> 式 | F26: =VLOOKUP(0,データ!$A25:$I$32,8,FALSE) -> 1270000 | G26: =VLOOKUP(0,データ!$A25:$I$32,9,FALSE) -> 889000 | H26: =F26-G26 -> 381000 | I26: =ROUND(H26/F26,3) -> 0.3
A27: 25 | B27: 端数値引き | F27: -206 | H27: =F27-G27 -> -206 | I27: =ROUND(H27/F27,3) -> 1 | L27: ↑↑セル範囲は調整する↑↑
B28: 小計 | F28: =SUM(F3:F27) -> 32701000 | G28: =SUM(G3:G27) -> 21888751 | H28: =F28-G28 -> 10812249 | I28: =ROUND(H28/F28,3) -> 0.331 | K28: 諸経費用計算式 | L28: ROUND(SUM(F2:F25)*0.15,0)
B29: 外構ｷｬﾝﾍﾟｰﾝ（外構契約100万円以上、宅配BOXｻｰﾋﾞｽ）有 | H29: =F29-G29 -> 0 | I29: =ROUND(H29/F29,3) -> #DIV/0!
B30: （現場見学会開催特典：家具）家具30万円分ｻｰﾋﾞｽ | G30: 225000 | H30: =F30-G30 -> -225000 | I30: =ROUND(H30/F30,3) -> #DIV/0!
B31: 合計（ｷｬﾝﾍﾟｰﾝ等を原価に計上した粗利率） | F31: =SUM(F28:F30) -> 32701000 | G31: =SUM(G28:G30) -> 22113751 | H31: =F31-G31 -> 10587249 | I31: =ROUND(H31/F31,3) -> 0.324
L33: ▼▼この下の欄に入力すると、左の図に反映されます▼▼
C34: 【特記事項】 | K34: お客様名 | L34: 古居徹朗様・古居百恵様 | N34: 見積担当 | O34: 設計担当 | P34: 設計課長 | Q34: 設計部長 | R34: 工事部長 | S34: 営業部長 | T34: 本部長 | U34: 社長
C35: ・新仕様Ver.2507(13) | K35: 提出日/契約日 | L35: 45939
C36: ・外構ｷｬﾝﾍﾟｰﾝ有り予定 | K36: 営業担当（敬称略） | L36: 堀川
C37: ・現場見学会開催 | K37: 契約時値引額 | L37: 0
C38: 家具ｻｰﾋﾞｽ有 | K38: 紹介：有 無 | L38: 無
B43: 【見積担当】
B44: 杉浦
B45: 中角
B46: 井圡
B47: 久野(麻）
B48: 久野(太）
B49: 中村
B50: 塚本
